python_facebook_lite-0.1.3.dist-info/licenses/LICENSE
pythonfacebook/__init__.py
pythonfacebook/endpoints.py
pythonfacebook/enums.py
pythonfacebook/exceptions.py
pythonfacebook/facebook.py
pythonfacebook/__pycache__/__init__.cpython-312.pyc
pythonfacebook/__pycache__/endpoints.cpython-312.pyc
pythonfacebook/__pycache__/enums.cpython-312.pyc
pythonfacebook/__pycache__/facebook.cpython-312.pyc
python_facebook_lite-0.1.3.dist-info/METADATA
python_facebook_lite-0.1.3.dist-info/WHEEL
python_facebook_lite-0.1.3.dist-info/top_level.txt
python_facebook_lite-0.1.3.dist-info/RECORD
