Metadata-Version: 2.4
Name: python-facebook-lite
Version: 0.1.3
Summary: A simple Facebook interaction library.
Author-email: Vlad Andrei <contact@vlad.my>
License-Expression: MIT
Project-URL: Homepage, https://github.com/vladmycode/pythonfacebook
Project-URL: Repository, https://github.com/vladmycode/pythonfacebook
Classifier: Programming Language :: Python :: 3
Classifier: Operating System :: OS Independent
Requires-Python: >=3.8
License-File: LICENSE
Requires-Dist: requests
Dynamic: license-file
